{"name":"LogInTest","id":"org.example.features.search.ParamTest:LogInTest","testCaseName":"org.example.features.search.ParamTest","testSteps":[{"number":1,"description":"Log in test ","duration":8506,"startTime":"2021-05-14T17:38:05.880746400+03:00[Europe/Bucharest]","result":"SUCCESS","precondition":false,"level":0,"children":[{"number":2,"description":"Accept cookies","duration":3197,"startTime":"2021-05-14T17:37:41.781092800+03:00[Europe/Bucharest]","screenshots":[{"screenshot":"90abd735eb180d8c091954b28cdf6d791dace9d868cd22d44f55ae8ad3e5fe99.png","timeStamp":1621003062707},{"screenshot":"2a5aabed811d9dff9b073c43c78a423e91608fe4cb6365059f7a54be90cba7a9.png","timeStamp":1621003064978}],"result":"SUCCESS","precondition":false,"level":1},{"number":3,"description":"Enters: ana_maria.1999@yahoo.com, testVVSS99","duration":1872,"startTime":"2021-05-14T17:37:44.987516200+03:00[Europe/Bucharest]","screenshots":[{"screenshot":"0cdaa859246c47982880c85fcd11a0d2f4436f51a8329f9b6eb3ce1cd5e0ed6e.png","timeStamp":1621003066859}],"result":"SUCCESS","precondition":false,"level":1},{"number":4,"description":"Login","duration":2440,"startTime":"2021-05-14T17:37:46.861654300+03:00[Europe/Bucharest]","screenshots":[{"screenshot":"3aafb63df419ea9b9408d44c2c08e4794c32d93c9cf178eb44bb21d68694889c.png","timeStamp":1621003069302}],"result":"SUCCESS","precondition":false,"level":1},{"number":5,"description":"Should see header: Ana Asmarandei","duration":997,"startTime":"2021-05-14T17:37:49.303123100+03:00[Europe/Bucharest]","screenshots":[{"screenshot":"6c8164e9ba549ae755a720bab77a03927f4cfb1c5ca6bce7bd8951dbc5eca714.png","timeStamp":1621003070298}],"result":"SUCCESS","precondition":false,"level":1}]},{"number":6,"description":"Log in test ","duration":6421,"startTime":"2021-05-14T17:38:05.880746400+03:00[Europe/Bucharest]","result":"SUCCESS","precondition":false,"level":0,"children":[{"number":7,"description":"Accept cookies","duration":1964,"startTime":"2021-05-14T17:37:57.518628900+03:00[Europe/Bucharest]","screenshots":[{"screenshot":"1c65d72f30cf42a397ecabc645820b7923114ed936918e80a2bac781409ac6ee.png","timeStamp":1621003078237},{"screenshot":"3dd81bb686fbabe1710709645e2ecef6f80fad31690701e91e4ef9b9b8d10282.png","timeStamp":1621003079483}],"result":"SUCCESS","precondition":false,"level":1},{"number":8,"description":"Enters: ana_maria.1999@yahoo.com, testVVSS9","duration":2371,"startTime":"2021-05-14T17:37:59.484371700+03:00[Europe/Bucharest]","screenshots":[{"screenshot":"d91c647afa5f6ae5181d002f59226dd15162222d3abc454f8aa3a6f3ea08dd56.png","timeStamp":1621003081825}],"result":"SUCCESS","precondition":false,"level":1},{"number":9,"description":"Login","duration":1314,"startTime":"2021-05-14T17:38:01.858021700+03:00[Europe/Bucharest]","screenshots":[{"screenshot":"7ee7c96d4147a4b75495800ac37daf702831a57a51f93b8cb22bef98a41e5734.png","timeStamp":1621003083172}],"result":"SUCCESS","precondition":false,"level":1},{"number":10,"description":"Should see header: failed","duration":772,"startTime":"2021-05-14T17:38:03.174499900+03:00[Europe/Bucharest]","screenshots":[{"screenshot":"a04b00cd4334cb5018227347d0a5fdac16d5ae15e7cd41c6a269d018011b17a9.png","timeStamp":1621003083946}],"result":"SUCCESS","precondition":false,"level":1}]}],"userStory":{"id":"org.example.features.search.ParamTest","storyName":"Param test","storyClassName":"org.example.features.search.ParamTest","path":"search","type":"story"},"featureTag":{"name":"Search/Param test","type":"story","displayName":"Search/Param test"},"title":"Log in test","coreIssues":["#La-jumatateP"],"tags":[{"name":"chrome","type":"context","displayName":"chrome"},{"name":"Search/Param test","type":"story","displayName":"Param test"},{"name":"Search","type":"feature","displayName":"Search"},{"name":"Search","type":"capability","displayName":"Search for definitions"}],"startTime":"2021-05-14T17:38:05.325230800+03:00[Europe/Bucharest]","duration":0,"isManualTestingUpToDate":false,"context":"chrome","dataTable":{"headers":["email","pass","found"],"rows":[{"values":["ana_maria.1999@yahoo.com","testVVSS99","Ana Asmarandei"],"result":"SUCCESS"},{"values":["ana_maria.1999@yahoo.com","testVVSS9","failed"],"result":"SUCCESS"}],"predefinedRows":false,"dataSetDescriptors":[{"startRow":0,"rowCount":0}]},"manual":false,"result":"SUCCESS","issues":["#La-jumatateP"]}